roy/__init__.py
roy/app/__init__.py
roy/app/base.py
roy/app/bin.py
roy/app/settings.py
roy/app/utils.py
roy/app/tests/settings.py
roy/app/tests/test_base.py
roy/app/tests/test_settings.py
roy/app/tests/component/__init__.py
roy/app/tests/component/app.py
roy/deploy/.DS_Store
roy/deploy/__init__.py
roy/deploy/app.py
roy/deploy/bin.py
roy/deploy/manager.py
roy/deploy/settings.py
roy/deploy/tasks.py
roy/deploy/components/.DS_Store
roy/deploy/components/__init__.py
roy/deploy/components/django.py
roy/deploy/components/nfs.py
roy/deploy/components/python.py
roy/deploy/components/systemd.py
roy/deploy/components/app/__init__.py
roy/deploy/components/app/app.service
roy/deploy/components/app/app.sh
roy/deploy/components/app/ipv4.rules
roy/deploy/components/iptables/__init__.py
roy/deploy/components/iptables/app.service
roy/deploy/components/iptables/custom.rules
roy/deploy/components/iptables/ipv4.rules
roy/deploy/components/nginx/__init__.py
roy/deploy/components/nginx/ipv4.rules
roy/deploy/components/nginx/proxy.conf
roy/deploy/components/nginx/server.conf
roy/deploy/components/nginx/server.service
roy/deploy/components/nginx/static.conf
roy/deploy/components/postgres/__init__.py
roy/deploy/components/postgres/ipv4.rules
roy/deploy/components/postgres/pg_hba.conf
roy/deploy/components/postgres/postgresql.conf
roy/deploy/components/postgres/server.service
roy/deploy/components/redis/__init__.py
roy/deploy/components/redis/ipv4.rules
roy/deploy/components/redis/server.conf
roy/deploy/components/redis/server.service
roy/deploy/providers/Vagrantfile
roy/deploy/providers/__init__.py
roy/deploy/providers/vagrant.py
roy/deploy/providers/vultr.py
roy/utils/__init__.py
roy/utils/collections.py
roy/utils/files.py
roy/utils/os.py
roy/utils/tasks.py
roy/utils/tests/test_tasks.py
roy-0.5.dist-info/LICENSE
roy-0.5.dist-info/METADATA
roy-0.5.dist-info/WHEEL
roy-0.5.dist-info/entry_points.txt
roy-0.5.dist-info/top_level.txt
roy-0.5.dist-info/zip-safe
roy-0.5.dist-info/RECORD
