Metadata-Version: 2.1
Name: roy
Version: 0.5
Summary: Deploy and app configuration made easy.
Home-page: http://github.com/royprojectcom/roy
Author: Morty Space
Author-email: morty.space@gmail.com
License: MIT
Platform: UNKNOWN
Classifier: Development Status :: 4 - Beta
Classifier: Intended Audience :: Developers
Classifier: License :: OSI Approved :: MIT License
Classifier: Natural Language :: English
Classifier: Operating System :: OS Independent
Classifier: Programming Language :: Python
Classifier: Programming Language :: Python :: 3.9
Classifier: Programming Language :: Python :: Implementation :: CPython
Classifier: Topic :: Software Development :: Libraries :: Application Frameworks
Classifier: Topic :: Software Development :: Libraries :: Python Modules
License-File: LICENSE
Requires-Dist: cerberus
Requires-Dist: jinja2
Requires-Dist: watchgod
Provides-Extra: dev
Requires-Dist: pylint ; extra == 'dev'
Requires-Dist: pycodestyle ; extra == 'dev'
Requires-Dist: pytest ; extra == 'dev'
Requires-Dist: pytest-cov ; extra == 'dev'
Requires-Dist: pytest-env ; extra == 'dev'
Requires-Dist: pytest-pythonpath ; extra == 'dev'
Requires-Dist: autopep8 ; extra == 'dev'
Requires-Dist: sphinx ; extra == 'dev'
Requires-Dist: twine ; extra == 'dev'
Requires-Dist: setuptools ; extra == 'dev'
Requires-Dist: wheel ; extra == 'dev'
